pollux_application/__init__.py
pollux_application/application_abstract.py
pollux_application/power2heat/__init__.py
pollux_application/power2heat/p2heat_solver.py
pollux_application/power2hydrogen/__init__.py
pollux_application/power2hydrogen/p2h2_solver.py
pollux_application-0.2.2.dist-info/LICENSE
pollux_application-0.2.2.dist-info/METADATA
pollux_application-0.2.2.dist-info/WHEEL
pollux_application-0.2.2.dist-info/RECORD
